setup.py
hangrypy/__init__.py
hangrypy/default_recipe_parser.py
hangrypy/foodnetwork.py
hangrypy/recipe.py
hangrypy/schema_org_recipe_parser.py
hangrypy.egg-info/PKG-INFO
hangrypy.egg-info/SOURCES.txt
hangrypy.egg-info/dependency_links.txt
hangrypy.egg-info/requires.txt
hangrypy.egg-info/top_level.txt