Metadata-Version: 1.1
Name: hangrypy
Version: 1.0
Summary: Parse recipies from microformats similar to the hangry gem
Home-page: https://github.com/scttcper/hangry-py
Author: Scott Cooper
Author-email: scttcper@gmail.com
License: UNKNOWN
Download-URL: https://github.com/scttcper/hangry-py/tarball/0.1
Keywords: hangry,recipe,parser,isodate
Platform: UNKNOWN
